[
  {
    "title": "Aldorin Spellweaver",
    "thumbnail": "aldorin_spellweaver",
    "material": "Vinyl"
  },
  {
    "title": "Aric Shadowstep",
    "thumbnail": "aric_shadowstep",
    "material": "Vinyl"
  },
  {
    "title": "Daiki Takara",
    "thumbnail": "daiki_takara",
    "material": "Acrylic"
  },
  {
    "title": "Lythran Moonshadow",
    "thumbnail": "lythrana_moonshadow",
    "material": "Acrylic"
  },
  {
    "title": "Zaporozhian Cossack",
    "thumbnail": "cossack",
    "material": "Acrylic"
  },
  {
    "title": "Wukong",
    "thumbnail": "wukong",
    "material": "Vinyl"
  },
  {
    "title": "Sir Gareth the Valiant",
    "thumbnail": "sir_gareth_the_valiant",
    "material": "Acrylic"
  },
  {
    "title": "Kratos",
    "thumbnail": "kratos",
    "material": "Acrylic"
  },
  {
    "title": "Verity Blake",
    "thumbnail": "verity_blake",
    "material": "Acrylic"
  },
  {
    "title": "Buck Wild",
    "thumbnail": "buck_wild",
    "material": "Acrylic"
  },
  {
    "title": "Hiroshi Kurogane",
    "thumbnail": "hiroshi_kurogane",
    "material": "Acrylic"
  },
  {
    "title": "Thalnoth Thunderous",
    "thumbnail": "thalnoth_thunderous",
    "material": "Acrylic"
  }
]
